{"shiller_cape": [{"date": "2009-01-01", "value": 13.3}, {"date": "2010-01-01", "value": 20.5}, {"date": "2011-01-01", "value": 23.4}, {"date": "2012-01-01", "value": 21.2}, {"date": "2013-01-01", "value": 22.2}, {"date": "2014-01-01", "value": 25.7}, {"date": "2015-01-01", "value": 27.2}, {"date": "2016-01-01", "value": 24.3}, {"date": "2017-01-01", "value": 28.1}, {"date": "2018-01-01", "value": 33.4}, {"date": "2019-01-01", "value": 29.6}, {"date": "2020-01-01", "value": 30.9}, {"date": "2021-01-01", "value": 34.8}, {"date": "2022-01-01", "value": 38.3}, {"date": "2022-07-01", "value": 28.2}, {"date": "2023-01-01", "value": 29.0}, {"date": "2023-07-01", "value": 31.2}, {"date": "2024-01-01", "value": 33.0}, {"date": "2024-07-01", "value": 35.8}, {"date": "2025-01-01", "value": 37.2}, {"date": "2025-07-01", "value": 34.1}, {"date": "2026-01-01", "value": 35.8}, {"date": "2026-04-01", "value": 34.2}], "forward_pe_spx": [{"date": "2019-01-01", "value": 14.8}, {"date": "2019-07-01", "value": 16.9}, {"date": "2020-01-01", "value": 18.9}, {"date": "2020-07-01", "value": 22.4}, {"date": "2021-01-01", "value": 22.8}, {"date": "2021-07-01", "value": 21.6}, {"date": "2022-01-01", "value": 20.2}, {"date": "2022-07-01", "value": 16.1}, {"date": "2023-01-01", "value": 17.0}, {"date": "2023-07-01", "value": 19.5}, {"date": "2024-01-01", "value": 19.9}, {"date": "2024-07-01", "value": 21.3}, {"date": "2025-01-01", "value": 22.0}, {"date": "2025-07-01", "value": 20.5}, {"date": "2026-01-01", "value": 21.8}, {"date": "2026-04-01", "value": 20.3}], "sector_pe": [{"sector": "Technology", "pe": 28.4, "eps_growth": 14.2, "div_yield": 0.7, "ytd": 8.2}, {"sector": "Financials", "pe": 13.8, "eps_growth": 8.1, "div_yield": 2.1, "ytd": 2.1}, {"sector": "Healthcare", "pe": 17.2, "eps_growth": 7.3, "div_yield": 1.8, "ytd": -4.2}, {"sector": "Consumer Disc.", "pe": 24.1, "eps_growth": 12.4, "div_yield": 0.9, "ytd": 3.8}, {"sector": "Industrials", "pe": 20.3, "eps_growth": 9.2, "div_yield": 1.4, "ytd": -1.2}, {"sector": "Energy", "pe": 11.2, "eps_growth": -3.1, "div_yield": 4.2, "ytd": -12.4}, {"sector": "Materials", "pe": 16.8, "eps_growth": 5.6, "div_yield": 2.0, "ytd": -3.1}, {"sector": "Utilities", "pe": 17.4, "eps_growth": 4.1, "div_yield": 3.4, "ytd": -5.8}, {"sector": "Comm. Services", "pe": 22.5, "eps_growth": 11.3, "div_yield": 0.9, "ytd": 5.4}, {"sector": "Cons. Staples", "pe": 19.1, "eps_growth": 3.8, "div_yield": 2.6, "ytd": -6.1}, {"sector": "Real Estate", "pe": 38.2, "eps_growth": 4.2, "div_yield": 3.8, "ytd": 0.4}], "pct_above_200ma": [{"date": "2023-01-01", "value": 42.0}, {"date": "2023-04-01", "value": 62.0}, {"date": "2023-07-01", "value": 71.0}, {"date": "2023-10-01", "value": 48.0}, {"date": "2024-01-01", "value": 74.0}, {"date": "2024-04-01", "value": 68.0}, {"date": "2024-07-01", "value": 65.0}, {"date": "2024-10-01", "value": 72.0}, {"date": "2025-01-01", "value": 58.0}, {"date": "2025-04-01", "value": 55.0}, {"date": "2025-07-01", "value": 61.0}, {"date": "2025-10-01", "value": 67.0}, {"date": "2026-01-01", "value": 53.0}, {"date": "2026-04-01", "value": 41.0}], "pct_above_50ma": [{"date": "2023-01-01", "value": 38.0}, {"date": "2023-04-01", "value": 58.0}, {"date": "2023-07-01", "value": 68.0}, {"date": "2023-10-01", "value": 29.0}, {"date": "2024-01-01", "value": 71.0}, {"date": "2024-04-01", "value": 55.0}, {"date": "2024-07-01", "value": 47.0}, {"date": "2024-10-01", "value": 62.0}, {"date": "2025-01-01", "value": 49.0}, {"date": "2025-04-01", "value": 43.0}, {"date": "2025-07-01", "value": 55.0}, {"date": "2025-10-01", "value": 60.0}, {"date": "2026-01-01", "value": 44.0}, {"date": "2026-04-01", "value": 27.0}], "new_highs_lows": [{"date": "2023-01-01", "value": 42}, {"date": "2023-04-01", "value": 128}, {"date": "2023-07-01", "value": 187}, {"date": "2023-10-01", "value": -65}, {"date": "2024-01-01", "value": 201}, {"date": "2024-04-01", "value": 85}, {"date": "2024-07-01", "value": 112}, {"date": "2024-10-01", "value": 154}, {"date": "2025-01-01", "value": 63}, {"date": "2025-04-01", "value": -28}, {"date": "2025-07-01", "value": 97}, {"date": "2025-10-01", "value": 134}, {"date": "2026-01-01", "value": 42}, {"date": "2026-04-01", "value": -118}], "mcclellan": [{"date": "2023-01-01", "value": -45}, {"date": "2023-04-01", "value": 62}, {"date": "2023-07-01", "value": 88}, {"date": "2023-10-01", "value": -112}, {"date": "2024-01-01", "value": 124}, {"date": "2024-04-01", "value": -18}, {"date": "2024-07-01", "value": 32}, {"date": "2024-10-01", "value": 78}, {"date": "2025-01-01", "value": -22}, {"date": "2025-04-01", "value": -67}, {"date": "2025-07-01", "value": 45}, {"date": "2025-10-01", "value": 91}, {"date": "2026-01-01", "value": -34}, {"date": "2026-04-01", "value": -156}], "factor_performance": {"MTUM": [{"date": "2025-04-01", "value": -4.2}, {"date": "2025-07-01", "value": 8.3}, {"date": "2025-10-01", "value": 12.1}, {"date": "2026-01-01", "value": 6.8}, {"date": "2026-04-01", "value": 3.9}], "VLUE": [{"date": "2025-04-01", "value": 2.1}, {"date": "2025-07-01", "value": 4.2}, {"date": "2025-10-01", "value": 6.8}, {"date": "2026-01-01", "value": 1.2}, {"date": "2026-04-01", "value": 1.8}], "QUAL": [{"date": "2025-04-01", "value": 1.8}, {"date": "2025-07-01", "value": 6.1}, {"date": "2025-10-01", "value": 9.4}, {"date": "2026-01-01", "value": 4.2}, {"date": "2026-04-01", "value": 2.7}], "USMV": [{"date": "2025-04-01", "value": 3.2}, {"date": "2025-07-01", "value": 5.1}, {"date": "2025-10-01", "value": 7.2}, {"date": "2026-01-01", "value": 2.8}, {"date": "2026-04-01", "value": -0.2}], "IWF": [{"date": "2025-04-01", "value": -3.1}, {"date": "2025-07-01", "value": 9.8}, {"date": "2025-10-01", "value": 14.2}, {"date": "2026-01-01", "value": 7.1}, {"date": "2026-04-01", "value": 5.8}], "IWD": [{"date": "2025-04-01", "value": 2.8}, {"date": "2025-07-01", "value": 3.9}, {"date": "2025-10-01", "value": 5.8}, {"date": "2026-01-01", "value": 0.8}, {"date": "2026-04-01", "value": 0.9}]}, "cot_data": {"Gold": [{"date": "2025-01-07", "value": -68}, {"date": "2025-02-04", "value": -72}, {"date": "2025-03-04", "value": -78}, {"date": "2025-04-01", "value": -81}, {"date": "2025-05-06", "value": -75}, {"date": "2025-06-03", "value": -69}, {"date": "2025-07-01", "value": -63}, {"date": "2025-08-05", "value": -58}, {"date": "2025-09-02", "value": -52}, {"date": "2025-10-07", "value": -61}, {"date": "2025-11-04", "value": -65}, {"date": "2025-12-02", "value": -70}, {"date": "2026-01-06", "value": -74}, {"date": "2026-02-03", "value": -78}, {"date": "2026-03-03", "value": -82}, {"date": "2026-04-01", "value": -85}], "Crude Oil": [{"date": "2025-01-07", "value": -42}, {"date": "2025-02-04", "value": -38}, {"date": "2025-03-04", "value": -35}, {"date": "2025-04-01", "value": -28}, {"date": "2025-05-06", "value": -31}, {"date": "2025-06-03", "value": -44}, {"date": "2025-07-01", "value": -52}, {"date": "2025-08-05", "value": -48}, {"date": "2025-09-02", "value": -39}, {"date": "2025-10-07", "value": -33}, {"date": "2025-11-04", "value": -29}, {"date": "2025-12-02", "value": -36}, {"date": "2026-01-06", "value": -41}, {"date": "2026-02-03", "value": -53}, {"date": "2026-03-03", "value": -61}, {"date": "2026-04-01", "value": -68}], "S&P 500 Futures": [{"date": "2025-01-07", "value": -32}, {"date": "2025-02-04", "value": -28}, {"date": "2025-03-04", "value": -22}, {"date": "2025-04-01", "value": -18}, {"date": "2025-05-06", "value": 8}, {"date": "2025-06-03", "value": 14}, {"date": "2025-07-01", "value": 22}, {"date": "2025-08-05", "value": 18}, {"date": "2025-09-02", "value": 12}, {"date": "2025-10-07", "value": 24}, {"date": "2025-11-04", "value": 31}, {"date": "2025-12-02", "value": 28}, {"date": "2026-01-06", "value": 19}, {"date": "2026-02-03", "value": 8}, {"date": "2026-03-03", "value": -12}, {"date": "2026-04-01", "value": -28}], "10Y T-Note": [{"date": "2025-01-07", "value": 18}, {"date": "2025-02-04", "value": 12}, {"date": "2025-03-04", "value": 8}, {"date": "2025-04-01", "value": 21}, {"date": "2025-05-06", "value": 28}, {"date": "2025-06-03", "value": 32}, {"date": "2025-07-01", "value": 24}, {"date": "2025-08-05", "value": 19}, {"date": "2025-09-02", "value": 14}, {"date": "2025-10-07", "value": 8}, {"date": "2025-11-04", "value": -4}, {"date": "2025-12-02", "value": -11}, {"date": "2026-01-06", "value": -18}, {"date": "2026-02-03", "value": -22}, {"date": "2026-03-03", "value": -28}, {"date": "2026-04-01", "value": -34}], "USD Index": [{"date": "2025-01-07", "value": 42}, {"date": "2025-02-04", "value": 38}, {"date": "2025-03-04", "value": 31}, {"date": "2025-04-01", "value": 22}, {"date": "2025-05-06", "value": 14}, {"date": "2025-06-03", "value": 8}, {"date": "2025-07-01", "value": -4}, {"date": "2025-08-05", "value": -12}, {"date": "2025-09-02", "value": -18}, {"date": "2025-10-07", "value": -8}, {"date": "2025-11-04", "value": 6}, {"date": "2025-12-02", "value": 14}, {"date": "2026-01-06", "value": 22}, {"date": "2026-02-03", "value": 28}, {"date": "2026-03-03", "value": 18}, {"date": "2026-04-01", "value": -8}], "Copper": [{"date": "2025-01-07", "value": 12}, {"date": "2025-02-04", "value": 18}, {"date": "2025-03-04", "value": 24}, {"date": "2025-04-01", "value": 31}, {"date": "2025-05-06", "value": 28}, {"date": "2025-06-03", "value": 22}, {"date": "2025-07-01", "value": 16}, {"date": "2025-08-05", "value": 8}, {"date": "2025-09-02", "value": -4}, {"date": "2025-10-07", "value": 6}, {"date": "2025-11-04", "value": 14}, {"date": "2025-12-02", "value": 22}, {"date": "2026-01-06", "value": 31}, {"date": "2026-02-03", "value": 38}, {"date": "2026-03-03", "value": 42}, {"date": "2026-04-01", "value": 44}]}, "earnings_calendar": [{"ticker": "AAPL", "name": "Apple", "date": "2026-05-01", "time": "AMC", "eps_est": 1.61, "eps_prev": 1.53, "rev_est_b": 95.4, "surprise_pct": null, "sector": "Technology"}, {"ticker": "MSFT", "name": "Microsoft", "date": "2026-04-29", "time": "AMC", "eps_est": 3.21, "eps_prev": 2.94, "rev_est_b": 72.1, "surprise_pct": null, "sector": "Technology"}, {"ticker": "GOOGL", "name": "Alphabet", "date": "2026-04-29", "time": "AMC", "eps_est": 2.18, "eps_prev": 1.89, "rev_est_b": 89.3, "surprise_pct": null, "sector": "Technology"}, {"ticker": "META", "name": "Meta Platforms", "date": "2026-04-29", "time": "AMC", "eps_est": 5.28, "eps_prev": 4.71, "rev_est_b": 41.8, "surprise_pct": null, "sector": "Technology"}, {"ticker": "AMZN", "name": "Amazon", "date": "2026-05-01", "time": "AMC", "eps_est": 1.38, "eps_prev": 0.98, "rev_est_b": 158.2, "surprise_pct": null, "sector": "Cons. Disc."}, {"ticker": "NVDA", "name": "NVIDIA", "date": "2026-05-28", "time": "AMC", "eps_est": 0.89, "eps_prev": 0.61, "rev_est_b": 43.2, "surprise_pct": null, "sector": "Technology"}, {"ticker": "TSLA", "name": "Tesla", "date": "2026-04-22", "time": "AMC", "eps_est": 0.44, "eps_prev": 0.45, "rev_est_b": 21.6, "surprise_pct": null, "sector": "Cons. Disc."}, {"ticker": "JPM", "name": "JPMorgan Chase", "date": "2026-04-11", "time": "BMO", "eps_est": 4.61, "eps_prev": 4.44, "rev_est_b": 46.2, "surprise_pct": 9.8, "sector": "Financials"}, {"ticker": "GS", "name": "Goldman Sachs", "date": "2026-04-14", "time": "BMO", "eps_est": 11.24, "eps_prev": 11.58, "rev_est_b": 15.4, "surprise_pct": 12.3, "sector": "Financials"}, {"ticker": "MS", "name": "Morgan Stanley", "date": "2026-04-16", "time": "BMO", "eps_est": 2.21, "eps_prev": 2.02, "rev_est_b": 16.8, "surprise_pct": 7.2, "sector": "Financials"}, {"ticker": "BAC", "name": "Bank of America", "date": "2026-04-15", "time": "BMO", "eps_est": 0.82, "eps_prev": 0.76, "rev_est_b": 26.8, "surprise_pct": 4.9, "sector": "Financials"}, {"ticker": "JNJ", "name": "Johnson & Johnson", "date": "2026-04-15", "time": "BMO", "eps_est": 2.58, "eps_prev": 2.71, "rev_est_b": 22.1, "surprise_pct": 2.1, "sector": "Healthcare"}, {"ticker": "LLY", "name": "Eli Lilly", "date": "2026-04-30", "time": "BMO", "eps_est": 3.42, "eps_prev": 2.58, "rev_est_b": 12.8, "surprise_pct": null, "sector": "Healthcare"}, {"ticker": "UNH", "name": "UnitedHealth", "date": "2026-04-15", "time": "BMO", "eps_est": 7.29, "eps_prev": 6.91, "rev_est_b": 102.3, "surprise_pct": -18.4, "sector": "Healthcare"}, {"ticker": "AMZN", "name": "Amazon", "date": "2026-05-01", "time": "AMC", "eps_est": 1.38, "eps_prev": 0.98, "rev_est_b": 158.2, "surprise_pct": null, "sector": "Cons. Disc."}, {"ticker": "MCD", "name": "McDonald's", "date": "2026-04-29", "time": "BMO", "eps_est": 3.06, "eps_prev": 2.98, "rev_est_b": 6.2, "surprise_pct": null, "sector": "Cons. Disc."}, {"ticker": "CAT", "name": "Caterpillar", "date": "2026-04-29", "time": "BMO", "eps_est": 4.82, "eps_prev": 5.28, "rev_est_b": 14.2, "surprise_pct": null, "sector": "Industrials"}, {"ticker": "BA", "name": "Boeing", "date": "2026-04-23", "time": "BMO", "eps_est": -2.1, "eps_prev": -1.13, "rev_est_b": 19.8, "surprise_pct": null, "sector": "Industrials"}, {"ticker": "XOM", "name": "ExxonMobil", "date": "2026-05-02", "time": "BMO", "eps_est": 1.82, "eps_prev": 2.06, "rev_est_b": 84.2, "surprise_pct": null, "sector": "Energy"}, {"ticker": "CVX", "name": "Chevron", "date": "2026-05-02", "time": "BMO", "eps_est": 2.18, "eps_prev": 2.55, "rev_est_b": 48.1, "surprise_pct": null, "sector": "Energy"}]}